Workbook

Sheet Instrucciones
A1: GUION DE PRUEBAS — MODELOS DE SAP ANALYTICS CLOUD (SAC)
A3: Objetivo
A4: Validar que los modelos de planeación de SAC (Ingresos, Costos y Gastos y Estados Financieros) funcionan correctamente en datos, cálculos, versiones, seguridad y reportes, antes de su puesta en productivo.
A6: Alcance
A7: Aplica a los tres modelos de las sociedades del programa. Cubre pruebas de datos maestros, integración, Data Actions, versiones/escenarios, entrada de datos, seguridad (DAC), reportes, conciliación y rendimiento.
A9: Cómo usar
A10: Ejecute cada caso de la hoja «Casos de Prueba», registre el Estado (Pendiente/Aprobado/Fallido/Bloqueado/No aplica), el resultado obtenido, el tester, la fecha y la evidencia. Los fallos se registran en la hoja «Defectos». La hoja «Resumen» muestra el avance automáticamente.
A13: Leyenda de estados
A14: Pendiente | B14: Aprobado | C14: Fallido | D14: Bloqueado | E14: No aplica
A16: Buenas prácticas de SAP consideradas
A17: • Ejecutar las pruebas en un tenant/entorno de prueba, nunca en productivo.
A18: • Validar la integridad de datos maestros y jerarquías antes de probar cálculos.
A19: • Usar versiones privadas para probar Data Actions y publicar solo lo aprobado.
A20: • Comparar cada Data Action contra un cálculo manual o un valor esperado conocido.
A21: • Conciliar los datos importados contra la fuente (DataSphere / ERP / Silotrans).
A22: • Probar la seguridad con usuarios de distintos roles e incluir pruebas negativas (DAC).
A23: • Verificar la gestión de versiones: copia, publicación y bloqueo de datos (Data Locking).
A24: • Medir el rendimiento de Data Actions y stories con volúmenes representativos.
A25: • Documentar evidencia (capturas) y registrar cada fallo como defecto con su severidad.
A26: • Mantener la trazabilidad requerimiento ↔ caso de prueba y ejecutar regresión tras cada cambio.

Sheet Resumen
A1: RESUMEN DE EJECUCIÓN DE PRUEBAS
A3: Total de casos | B3: =COUNTA('Casos de Prueba'!A3:A40) | D3: Por estado
A4: Ejecutados | B4: =COUNTIF('Casos de Prueba'!I3:I40,"<>Pendiente")-COUNTBLANK('Casos de Prueba'!I3:I40) | D4: Estado | E4: Casos
A5: Aprobados | B5: =COUNTIF('Casos de Prueba'!I3:I40,"Aprobado") | D5: Pendiente | E5: =COUNTIF('Casos de Prueba'!I3:I40,"Pendiente")
A6: Fallidos | B6: =COUNTIF('Casos de Prueba'!I3:I40,"Fallido") | D6: Aprobado | E6: =COUNTIF('Casos de Prueba'!I3:I40,"Aprobado")
A7: % ejecución | B7: =IFERROR((COUNTA('Casos de Prueba'!A3:A40)-COUNTIF('Casos de Prueba'!I3:I40,"Pendiente"))/COUNTA('Casos de Prueba'!A3:A40),0) | D7: Fallido | E7: =COUNTIF('Casos de Prueba'!I3:I40,"Fallido")
A8: % aprobación | B8: =IFERROR(COUNTIF('Casos de Prueba'!I3:I40,"Aprobado")/COUNTA('Casos de Prueba'!A3:A40),0) | D8: Bloqueado | E8: =COUNTIF('Casos de Prueba'!I3:I40,"Bloqueado")
D9: No aplica | E9: =COUNTIF('Casos de Prueba'!I3:I40,"No aplica")
A10: Por categoría
A11: Categoría | B11: Casos | C11: Aprobados
A12: Datos maestros y dimensiones | B12: =COUNTIF('Casos de Prueba'!C3:C40,"Datos maestros y dimensiones") | C12: =COUNTIFS('Casos de Prueba'!C3:C40,"Datos maestros y dimensiones",'Casos de Prueba'!I3:I40,"Aprobado")
A13: Integración de datos | B13: =COUNTIF('Casos de Prueba'!C3:C40,"Integración de datos") | C13: =COUNTIFS('Casos de Prueba'!C3:C40,"Integración de datos",'Casos de Prueba'!I3:I40,"Aprobado")
A14: Cálculos (Data Actions) | B14: =COUNTIF('Casos de Prueba'!C3:C40,"Cálculos (Data Actions)") | C14: =COUNTIFS('Casos de Prueba'!C3:C40,"Cálculos (Data Actions)",'Casos de Prueba'!I3:I40,"Aprobado")
A15: Versiones y escenarios | B15: =COUNTIF('Casos de Prueba'!C3:C40,"Versiones y escenarios") | C15: =COUNTIFS('Casos de Prueba'!C3:C40,"Versiones y escenarios",'Casos de Prueba'!I3:I40,"Aprobado")
A16: Entrada de datos | B16: =COUNTIF('Casos de Prueba'!C3:C40,"Entrada de datos") | C16: =COUNTIFS('Casos de Prueba'!C3:C40,"Entrada de datos",'Casos de Prueba'!I3:I40,"Aprobado")
A17: Seguridad y autorizaciones | B17: =COUNTIF('Casos de Prueba'!C3:C40,"Seguridad y autorizaciones") | C17: =COUNTIFS('Casos de Prueba'!C3:C40,"Seguridad y autorizaciones",'Casos de Prueba'!I3:I40,"Aprobado")
A18: Reportes y dashboards | B18: =COUNTIF('Casos de Prueba'!C3:C40,"Reportes y dashboards") | C18: =COUNTIFS('Casos de Prueba'!C3:C40,"Reportes y dashboards",'Casos de Prueba'!I3:I40,"Aprobado")
A19: Conciliación | B19: =COUNTIF('Casos de Prueba'!C3:C40,"Conciliación") | C19: =COUNTIFS('Casos de Prueba'!C3:C40,"Conciliación",'Casos de Prueba'!I3:I40,"Aprobado")
A20: Rendimiento | B20: =COUNTIF('Casos de Prueba'!C3:C40,"Rendimiento") | C20: =COUNTIFS('Casos de Prueba'!C3:C40,"Rendimiento",'Casos de Prueba'!I3:I40,"Aprobado")
A21: Regresión / general | B21: =COUNTIF('Casos de Prueba'!C3:C40,"Regresión / general") | C21: =COUNTIFS('Casos de Prueba'!C3:C40,"Regresión / general",'Casos de Prueba'!I3:I40,"Aprobado")

Sheet Listas
A1: Estados | B1: Prioridad | C1: Modelos | D1: Categorías | E1: EstadoDefecto | F1: Severidad
A2: Pendiente | B2: Alta | C2: Ingresos | D2: Datos maestros y dimensiones | E2: Abierto | F2: Crítica
A3: Aprobado | B3: Media | C3: Costos y Gastos | D3: Integración de datos | E3: En análisis | F3: Alta
A4: Fallido | B4: Baja | C4: Estados Financieros | D4: Cálculos (Data Actions) | E4: En corrección | F4: Media
A5: Bloqueado | C5: Todos | D5: Versiones y escenarios | E5: Resuelto | F5: Baja
A6: No aplica | D6: Entrada de datos | E6: Cerrado
D7: Seguridad y autorizaciones
D8: Reportes y dashboards
D9: Conciliación
D10: Rendimiento
D11: Regresión / general

Sheet Casos de Prueba
A1: GUION DE PRUEBAS — MODELOS DE SAP ANALYTICS CLOUD (SAC)
A2: ID | B2: Caso de prueba | C2: Categoría | D2: Modelo | E2: Precondiciones | F2: Pasos | G2: Resultado esperado | H2: Prioridad | I2: Estado | J2: Resultado obtenido | K2: Tester | L2: Fecha | M2: Evidencia
A3: TC-001 | B3: Verificar dimensiones y jerarquías del modelo | C3: Datos maestros y dimensiones | D3: Todos | E3: Modelo creado; maestros importados | F3: Abrir el modelo y revisar las dimensiones (Cuenta, Sociedad, CEBE, CECO, Versión, Fecha) y sus jerarquías | G3: Todas las dimensiones y jerarquías existen, sin duplicados ni nodos huérfanos | H3: Alta | I3: Pendiente
A4: TC-002 | B4: Validar miembros de dimensión contra la fuente | C4: Datos maestros y dimensiones | D4: Todos | E4: Maestros disponibles en DataSphere | F4: Comparar el conteo y los valores de miembros (regionales, CECOs, cuentas) con la fuente | G4: Coinciden 100% con la fuente | H4: Alta | I4: Pendiente
A5: TC-003 | B5: Validar propiedades de la dimensión Cuenta | C5: Datos maestros y dimensiones | D5: Todos | E5: — | F5: Revisar tipo de cuenta (INC/EXP/AST/LEQ), agregación y signo de cada cuenta | G5: Cada cuenta tiene tipo, agregación y signo correctos | H5: Alta | I5: Pendiente
A6: TC-004 | B6: Validar descripciones y atributos de miembros | C6: Datos maestros y dimensiones | D6: Todos | E6: — | F6: Revisar descripciones y atributos de cuentas y centros | G6: Descripciones correctas y completas; sin miembros sin descripción | H6: Media | I6: Pendiente
A7: TC-010 | B7: Ejecutar importación del real desde DataSphere | C7: Integración de datos | D7: Todos | E7: Conexión a DataSphere configurada | F7: Ejecutar el flujo de importación del dato real para un periodo de prueba | G7: La importación finaliza sin errores | H7: Alta | I7: Pendiente
A8: TC-011 | B8: Conciliar saldos reales SAC vs. ERP | C8: Integración de datos | D8: Estados Financieros | E8: Real importado | F8: Comparar totales por cuenta y CEBE contra el balance del ERP | G8: Diferencia = 0 | H8: Alta | I8: Pendiente
A9: TC-012 | B9: Verificar el mapeo de campos (origen → dimensión/medida) | C9: Integración de datos | D9: Todos | E9: — | F9: Revisar que cada campo origen mapea a la dimensión o medida correcta | G9: Mapeo correcto; sin datos en «no asignado» | H9: Alta | I9: Pendiente
A10: TC-013 | B10: Probar el refresco programado del real | C10: Integración de datos | D10: Todos | E10: Calendario de refresco configurado | F10: Verificar la ejecución del refresco y su bitácora | G10: Refresco exitoso según el calendario | H10: Media | I10: Pendiente
A11: TC-014 | B11: Manejo de errores de importación (datos inválidos) | C11: Integración de datos | D11: Todos | E11: — | F11: Cargar un registro con un miembro inexistente | G11: El sistema rechaza el registro e informa el error con claridad | H11: Media | I11: Pendiente
A12: TC-020 | B12: Data Action de ingresos P×Q | C12: Cálculos (Data Actions) | D12: Ingresos | E12: Kilos y tarifa cargados | F12: Ejecutar la Data Action de P×Q sobre un juego de datos controlado | G12: Importe = Kilos × Tarifa (coincide con el cálculo manual) | H12: Alta | I12: Pendiente
A13: TC-021 | B13: Data Action de crecimiento (volumen y tarifa) | C13: Cálculos (Data Actions) | D13: Ingresos | E13: Base N-1 y % definidos | F13: Ejecutar la Data Action de crecimiento | G13: Resultado = base × (1 + %), por regional | H13: Alta | I13: Pendiente
A14: TC-022 | B14: Data Action de estacionalidad | C14: Cálculos (Data Actions) | D14: Ingresos | E14: Total anual calculado | F14: Ejecutar la Data Action de distribución mensual | G14: La suma mensual = total anual (100%) | H14: Alta | I14: Pendiente
... A40: TC-091 | B40: Trazabilidad requerimiento ↔ caso de prueba | C40: Regresión / general | D40: Todos | E40: — | F40: Verificar que cada caso enlaza a un requerimiento | G40: Cobertura completa de requerimientos | H40: Media | I40: Pendiente

Sheet Defectos
A1: REGISTRO DE DEFECTOS
A2: ID | B2: Caso (TC) | C2: Descripción | D2: Severidad | E2: Estado | F2: Responsable | G2: Fecha | H2: Resolución
A3: DEF-001 | B3: TC-024 | C3: (ejemplo) El P&G consolidado no cuadra por CEBE | D3: Alta | E3: Abierto | F3: (responsable) | H3: (pendiente)
