Workbook

Sheet Instrucciones
A1: Plantillas de carga para el add-in de SAC y reportes financieros – FANALCA
A2: Libro de ejemplo. Los miembros, IDs de modelo y cifras son ilustrativos: reemplácelos por los de sus modelos.
A5: Contenido del libro
A6: Carga_Ingresos | B6: Plantilla del modelo Ingresos FANALCA: UNIDADES y PRECIO por sociedad, Cebe, cliente y referencia, mes a mes.
A7: Carga_Gastos | B7: Plantilla del modelo Gastos FANALCA: gasto por sociedad, centro de costo, Cebe y cuenta.
A8: Carga_EEFF | B8: Balance proyectado en el formato del modelo EEFF FANALCA, listo para publicar.
A9: Carga_Plana | B9: Formato plano (una fila por mes) para el botón de carga de archivos de una historia o el Cargador de datos a SAC.
A10: PyG | B10: Estado de resultados mensual 2026 con márgenes.
A11: Balance | B11: Balance general mensual con control de cuadre.
A12: Flujo_Caja | B12: Flujo de caja por el método indirecto, conciliado con la caja del balance.
A13: Supuestos | B13: Parámetros de costo, capital de trabajo, inversión, deuda, impuestos y balance de apertura.
A14: Listas | B14: Miembros de las dimensiones que alimentan las listas desplegables.
A16: Convenciones de color
A17: 123.456 | B17: Amarillo con texto azul: valor que usted digita o pega en la tabla del add-in.
A18: FN_MOTOS | B18: Gris: miembros de las dimensiones (filas de la tabla del add-in).
A19: Vínculo | B19: Texto verde: valor que viene de otra hoja del libro.
A20: Fórmula | B20: Texto negro: fórmula. Gris cursiva: cálculo de referencia que SAC hace por su cuenta (no se publica).
A22: Cargar datos con el add-in de SAC para Excel
A23: 1. Conectar | B23: En Excel: pestaña SAP Analytics Cloud → Iniciar sesión con la URL de su tenant (por ejemplo https://fanalca.us10.hcs.cloud.sap).
A24: 2. Insertar tabla | B24: Insertar → Tabla → elija el modelo (Ingresos, Gastos o EEFF FANALCA). Ponga en filas las dimensiones de la plantilla y en columnas Date (meses de 2026).
A25: 3. Filtrar | B25: En el panel del diseñador fije la versión (por ejemplo public.Presupuesto_2026), Auditoria y Moneda como en el encabezado de la plantilla.
A26: 4. Habilitar planificación | B26: Menú contextual del modelo en el panel → Planificación habilitada. Sin esto las celdas no aceptan valores.
A27: 5. Pegar valores | B27: Copie las celdas amarillas y péguelas con Pegado especial → Valores en las mismas posiciones de la tabla. Si una combinación no existe aún, agréguela con "Agregar miembro" en la tabla (datos no reservados).
A28: 6. Publicar | B28: SAP Analytics Cloud → Publicar datos (o Guardar datos en la versión). Revise que no queden celdas rechazadas por bloqueos o control de acceso.
A29: 7. Calcular | B29: Si el modelo tiene data actions (por ejemplo el PxQ de ingresos), ejecútelas desde la historia o la multi action para calcular los derivados.
A31: Permisos que necesita el usuario (licencia Planning Standard)
A32: Rol | B32: Copia de Planner Reporter. Planning Model: Leer + Mantener + Ejecutar. No marcar Crear, Actualizar ni Eliminar (son de Planning Professional).
A33: Add-in Workbook | B33: Leer para usar libros guardados; Crear + Leer + Actualizar para crear y guardar libros en el repositorio de SAC.
A34: Modelo | B34: Compartido con el equipo con acceso de edición (Leer, Actualizar, Mantener).
A35: Datos | B35: Permiso de escritura en el control de acceso a datos de Sociedades / Cebes, celdas sin bloqueo y versión editable.
A36: Carga de archivos | B36: Para usar Carga_Plana con el botón de carga de una historia: Personal Data Acquisition = Ejecutar y un trabajo de carga creado por el modelador.
A38: Cómo se conectan los reportes
A39: PyG | B39: Ingresos = suma de ING_VENTAS_NAL (unidades × precio) por sociedad. Gastos por grupo de cuenta (51 administración, 52 ventas). Costo, depreciación, intereses e impuesto con los supuestos.
A40: Balance | B40: Cartera, inventarios y proveedores por días de rotación; PP&E con la inversión mensual; deuda con la amortización; patrimonio con la utilidad del P&L. La caja sale del flujo.
A41: Flujo_Caja | B41: Utilidad neta + depreciación − variaciones de capital de trabajo − inversión ± deuda. La caja final debe igualar la del balance; la fila de control del balance debe quedar en 0.

Sheet Carga_Ingresos
A1: Plantilla de carga: Ingresos FANALCA (add-in de SAC para Excel)
A2: Filas = Sociedades × Cebes × Clientes × Referencias × Ratio. Columnas = Date (mes). Digite UNIDADES y PRECIO; el ingreso lo calcula el data action PxQ en SAC.
A3: Fuente de datos (add-in)
A4: Modelo | B4: Modelo Ingresos FANALCA (Couh7ojg5e54rh2d4udijq6o83k)
A5: Versión | B5: public.Presupuesto_2026
A6: Auditoria | B6: PRESUPUESTO_EXCEL
A7: Moneda | B7: COP
A9: Sociedades | B9: Cebes | C9: Clientes | D9: Referencias | E9: Ratio | F9: Ene 2026 | G9: Feb 2026 | H9: Mar 2026 | I9: Abr 2026 | J9: May 2026 | K9: Jun 2026 | L9: Jul 2026 | M9: Ago 2026 | N9: Sep 2026 | O9: Oct 2026 | P9: Nov 2026 | Q9: Dic 2026 | R9: Total 2026
A10: FN_MOTOS | B10: CB_MOTOS | C10: CLI_001 | D10: REF_CB125 | E10: UNIDADES | F10: 1640 | G10: 1720 | H10: 1940 | I10: 1900 | J10: 2000 | K10: 2060 | L10: 1960 | M10: 2040 | N10: 2100 | O10: 2160 | P10: 2120 | Q10: 2360 | R10: =SUM(F10:Q10) -> 24000
A11: FN_MOTOS | B11: CB_MOTOS | C11: CLI_001 | D11: REF_CB125 | E11: PRECIO | F11: 9890000 | G11: 9890000 | H11: 9890000 | I11: 9890000 | J11: 9890000 | K11: 9890000 | L11: 10286000 | M11: 10286000 | N11: 10286000 | O11: 10286000 | P11: 10286000 | Q11: 10286000 | R11: =IFERROR(SUMPRODUCT(F10:Q10,F11:Q11)/R10,0) -> 10100210
A12: FN_MOTOS | B12: CB_MOTOS | C12: CLI_001 | D12: REF_CB125 | E12: ING_VENTAS_NAL | F12: =F10*F11 -> 16219600000 | G12: =G10*G11 -> 17010800000 | H12: =H10*H11 -> 19186600000 | I12: =I10*I11 -> 18791000000 | J12: =J10*J11 -> 19780000000 | K12: =K10*K11 -> 20373400000 | L12: =L10*L11 -> 20160560000 | M12: =M10*M11 -> 20983440000 | ... Q12: =Q10*Q11 -> 24274960000 | R12: =SUM(F12:Q12) -> 242405040000
A13: FN_MOTOS | B13: CB_MOTOS | C13: CLI_003 | D13: REF_XR190 | E13: UNIDADES | F13: 738 | G13: 774 | H13: 873 | I13: 855 | J13: 900 | K13: 927 | L13: 882 | M13: 918 | N13: 945 | O13: 972 | P13: 954 | Q13: 1062 | R13: =SUM(F13:Q13) -> 10800
A14: FN_MOTOS | B14: CB_MOTOS | C14: CLI_003 | D14: REF_XR190 | E14: PRECIO | F14: 14500000 | G14: 14500000 | H14: 14500000 | I14: 14500000 | J14: 14500000 | K14: 14500000 | L14: 15080000 | M14: 15080000 | N14: 15080000 | O14: 15080000 | P14: 15080000 | Q14: 15080000 | R14: =IFERROR(SUMPRODUCT(F13:Q13,F14:Q14)/R13,0) -> 14807883
A15: FN_MOTOS | B15: CB_MOTOS | C15: CLI_003 | D15: REF_XR190 | E15: ING_VENTAS_NAL | F15: =F13*F14 -> 10701000000 | G15: =G13*G14 -> 11223000000 | H15: =H13*H14 -> 12658500000 | I15: =I13*I14 -> 12397500000 | J15: =J13*J14 -> 13050000000 | K15: =K13*K14 -> 13441500000 | L15: =L13*L14 -> 13300560000 | M15: =M13*M14 -> 13843440000 | ... Q15: =Q13*Q14 -> 16014960000 | R15: =SUM(F15:Q15) -> 159925140000
A16: FN_AUTOS | B16: CB_AUTOS | C16: CLI_004 | D16: REF_CIVIC | E16: UNIDADES | F16: 49 | G16: 52 | H16: 58 | I16: 57 | J16: 60 | K16: 62 | L16: 59 | M16: 61 | N16: 63 | O16: 65 | P16: 64 | Q16: 71 | R16: =SUM(F16:Q16) -> 721
A17: FN_AUTOS | B17: CB_AUTOS | C17: CLI_004 | D17: REF_CIVIC | E17: PRECIO | F17: 145000000 | G17: 145000000 | H17: 145000000 | I17: 145000000 | J17: 145000000 | K17: 145000000 | L17: 150800000 | M17: 150800000 | N17: 150800000 | O17: 150800000 | P17: 150800000 | Q17: 150800000 | R17: =IFERROR(SUMPRODUCT(F16:Q16,F17:Q17)/R16,0) -> 1.48081e+08
A18: FN_AUTOS | B18: CB_AUTOS | C18: CLI_004 | D18: REF_CIVIC | E18: ING_VENTAS_NAL | F18: =F16*F17 -> 7105000000 | G18: =G16*G17 -> 7540000000 | H18: =H16*H17 -> 8410000000 | I18: =I16*I17 -> 8265000000 | J18: =J16*J17 -> 8700000000 | K18: =K16*K17 -> 8990000000 | L18: =L16*L17 -> 8897200000 | M18: =M16*M17 -> 9198800000 | ... Q18: =Q16*Q17 -> 10706800000 | R18: =SUM(F18:Q18) -> 106766400000
A19: FN_AUTOS | B19: CB_AUTOS | C19: CLI_005 | D19: REF_HRV | E19: UNIDADES | F19: 66 | G19: 69 | H19: 78 | I19: 76 | J19: 80 | K19: 82 | L19: 78 | M19: 82 | N19: 84 | O19: 86 | P19: 85 | Q19: 94 | R19: =SUM(F19:Q19) -> 960
A20: FN_AUTOS | B20: CB_AUTOS | C20: CLI_005 | D20: REF_HRV | E20: PRECIO | F20: 135000000 | G20: 135000000 | H20: 135000000 | I20: 135000000 | J20: 135000000 | K20: 135000000 | L20: 140400000 | M20: 140400000 | N20: 140400000 | O20: 140400000 | P20: 140400000 | Q20: 140400000 | R20: =IFERROR(SUMPRODUCT(F19:Q19,F20:Q20)/R19,0) -> 137863125
A21: FN_AUTOS | B21: CB_AUTOS | C21: CLI_005 | D21: REF_HRV | E21: ING_VENTAS_NAL | F21: =F19*F20 -> 8910000000 | G21: =G19*G20 -> 9315000000 | H21: =H19*H20 -> 10530000000 | I21: =I19*I20 -> 10260000000 | J21: =J19*J20 -> 10800000000 | K21: =K19*K20 -> 11070000000 | L21: =L19*L20 -> 10951200000 | M21: =M19*M20 -> 11512800000 | ... Q21: =Q19*Q20 -> 13197600000 | R21: =SUM(F21:Q21) -> 132348600000
A22: FN_TUBOS | B22: CB_TUBERIA | C22: CLI_002 | D22: REF_TUBO_2P | E22: UNIDADES | F22: 328000 | G22: 344000 | H22: 388000 | I22: 380000 | J22: 400000 | K22: 412000 | L22: 392000 | M22: 408000 | N22: 420000 | O22: 432000 | P22: 424000 | Q22: 472000 | R22: =SUM(F22:Q22) -> 4800000
A23: FN_TUBOS | B23: CB_TUBERIA | C23: CLI_002 | D23: REF_TUBO_2P | E23: PRECIO | F23: 18000 | G23: 18000 | H23: 18000 | I23: 18000 | J23: 18000 | K23: 18000 | L23: 18720 | M23: 18720 | N23: 18720 | O23: 18720 | P23: 18720 | Q23: 18720 | R23: =IFERROR(SUMPRODUCT(F22:Q22,F23:Q23)/R22,0) -> 18382.2
A24: FN_TUBOS | B24: CB_TUBERIA | C24: CLI_002 | D24: REF_TUBO_2P | E24: ING_VENTAS_NAL | F24: =F22*F23 -> 5904000000 | G24: =G22*G23 -> 6192000000 | H24: =H22*H23 -> 6984000000 | I24: =I22*I23 -> 6840000000 | J24: =J22*J23 -> 7200000000 | K24: =K22*K23 -> 7416000000 | L24: =L22*L23 -> 7338240000 | M24: =M22*M23 -> 7637760000 | ... Q24: =Q22*Q23 -> 8835840000 | R24: =SUM(F24:Q24) -> 88234560000
A25: FN_TUBOS | B25: CB_TUBERIA | C25: CLI_006 | D25: REF_TUBO_4P | E25: UNIDADES | F25: 123000 | G25: 129000 | H25: 145500 | I25: 142500 | J25: 150000 | K25: 154500 | L25: 147000 | M25: 153000 | N25: 157500 | O25: 162000 | P25: 159000 | Q25: 177000 | R25: =SUM(F25:Q25) -> 1800000
A26: FN_TUBOS | B26: CB_TUBERIA | C26: CLI_006 | D26: REF_TUBO_4P | E26: PRECIO | F26: 42000 | G26: 42000 | H26: 42000 | I26: 42000 | J26: 42000 | K26: 42000 | L26: 43680 | M26: 43680 | N26: 43680 | O26: 43680 | P26: 43680 | Q26: 43680 | R26: =IFERROR(SUMPRODUCT(F25:Q25,F26:Q26)/R25,0) -> 42891.8
A27: FN_TUBOS | B27: CB_TUBERIA | C27: CLI_006 | D27: REF_TUBO_4P | E27: ING_VENTAS_NAL | F27: =F25*F26 -> 5166000000 | G27: =G25*G26 -> 5418000000 | H27: =H25*H26 -> 6111000000 | I27: =I25*I26 -> 5985000000 | J27: =J25*J26 -> 6300000000 | K27: =K25*K26 -> 6489000000 | L27: =L25*L26 -> 6420960000 | M27: =M25*M26 -> 6683040000 | ... Q27: =Q25*Q26 -> 7731360000 | R27: =SUM(F27:Q27) -> 77205240000
A29: Notas
A30: 1. Celdas amarillas (texto azul): valores para digitar o pegar en la tabla del add-in. Columnas grises: miembros de las dimensiones.
A31: 2. Las filas ING_VENTAS_NAL (gris cursiva) muestran el PxQ como referencia: no las publique, el data action PxQ las calcula en SAC.
A32: 3. "Total 2026" lo calcula SAC; en el add-in no se escribe sobre totales. PRECIO total = precio promedio ponderado.
A33: 4. Si su tabla del add-in tiene otro orden de filas o columnas, pegue con Pegado especial → Valores respetando ese orden.

Sheet Carga_Gastos
A1: Plantilla de carga: Gastos FANALCA (add-in de SAC para Excel)
A2: Filas = Sociedades × Cecos × Cebes × Cuentas_Egresos. Columnas = Date (mes). Valores en COP.
A3: Fuente de datos (add-in)
A4: Modelo | B4: Modelo Gastos FANALCA (Cunejii8r2d7vr4ldq2ousgfg7f)
A5: Versión | B5: public.Presupuesto_2026
A6: Auditoria | B6: PRESUPUESTO_EXCEL
A7: Moneda | B7: COP
A9: Sociedades | B9: Cecos | C9: Cebes | D9: Cuentas_Egresos | E9: Ene 2026 | F9: Feb 2026 | G9: Mar 2026 | H9: Abr 2026 | I9: May 2026 | J9: Jun 2026 | K9: Jul 2026 | L9: Ago 2026 | M9: Sep 2026 | N9: Oct 2026 | O9: Nov 2026 | P9: Dic 2026 | Q9: Total 2026 | R9: Grupo P&L (ayuda, no se publica)
A10: FN_MOTOS | B10: CC_PLANTA | C10: CB_MOTOS | D10: 5105_SALARIOS | E10: 2400000000 | F10: 2400000000 | G10: 2400000000 | H10: 2400000000 | I10: 2400000000 | J10: 2400000000 | K10: 2520000000 | L10: 2520000000 | M10: 2520000000 | N10: 2520000000 | O10: 2520000000 | P10: 3720000000 | Q10: =SUM(E10:P10) -> 30720000000 | R10: =IFERROR(INDEX(Listas!$J$5:$J$11,MATCH(D10,Listas!$H$5:$H$11,0)),"Cuenta no encontrada") -> Gastos de administración
A11: FN_MOTOS | B11: CC_PLANTA | C11: CB_MOTOS | D11: 5145_MANTENIMIENTO | E11: 372400000 | F11: 380000000 | G11: 387600000 | H11: 372400000 | I11: 380000000 | J11: 387600000 | K11: 372400000 | L11: 380000000 | M11: 387600000 | N11: 372400000 | O11: 380000000 | P11: 387600000 | Q11: =SUM(E11:P11) -> 4560000000 | R11: =IFERROR(INDEX(Listas!$J$5:$J$11,MATCH(D11,Listas!$H$5:$H$11,0)),"Cuenta no encontrada") -> Gastos de administración
A12: FN_MOTOS | B12: CC_VENTAS | C12: CB_MOTOS | D12: 5205_SALARIOS_VENTAS | E12: 950000000 | F12: 950000000 | G12: 950000000 | H12: 950000000 | I12: 950000000 | J12: 950000000 | K12: 997500000 | L12: 997500000 | M12: 997500000 | N12: 997500000 | O12: 997500000 | P12: 997500000 | Q12: =SUM(E12:P12) -> 11685000000 | R12: =IFERROR(INDEX(Listas!$J$5:$J$11,MATCH(D12,Listas!$H$5:$H$11,0)),"Cuenta no encontrada") -> Gastos de ventas
A13: FN_MOTOS | B13: CC_VENTAS | C13: CB_MOTOS | D13: 5235_PUBLICIDAD | E13: 570400000 | F13: 620000000 | G13: 669600000 | H13: 570400000 | I13: 620000000 | J13: 669600000 | K13: 570400000 | L13: 620000000 | M13: 669600000 | N13: 570400000 | O13: 620000000 | P13: 669600000 | Q13: =SUM(E13:P13) -> 7440000000 | R13: =IFERROR(INDEX(Listas!$J$5:$J$11,MATCH(D13,Listas!$H$5:$H$11,0)),"Cuenta no encontrada") -> Gastos de ventas
A14: FN_MOTOS | B14: CC_LOGISTICA | C14: CB_MOTOS | D14: 5250_FLETES | E14: 523800000 | F14: 540000000 | G14: 556200000 | H14: 523800000 | I14: 540000000 | J14: 556200000 | K14: 523800000 | L14: 540000000 | M14: 556200000 | N14: 523800000 | O14: 540000000 | P14: 556200000 | Q14: =SUM(E14:P14) -> 6480000000 | R14: =IFERROR(INDEX(Listas!$J$5:$J$11,MATCH(D14,Listas!$H$5:$H$11,0)),"Cuenta no encontrada") -> Gastos de ventas
A15: FN_AUTOS | B15: CC_ADMIN | C15: CB_AUTOS | D15: 5105_SALARIOS | E15: 1150000000 | F15: 1150000000 | G15: 1150000000 | H15: 1150000000 | I15: 1150000000 | J15: 1150000000 | K15: 1207500000 | L15: 1207500000 | M15: 1207500000 | N15: 1207500000 | O15: 1207500000 | P15: 1782500000 | Q15: =SUM(E15:P15) -> 14720000000 | R15: =IFERROR(INDEX(Listas!$J$5:$J$11,MATCH(D15,Listas!$H$5:$H$11,0)),"Cuenta no encontrada") -> Gastos de administración
A16: FN_AUTOS | B16: CC_ADMIN | C16: CB_AUTOS | D16: 5110_HONORARIOS | E16: 210000000 | F16: 210000000 | G16: 210000000 | H16: 210000000 | I16: 210000000 | J16: 210000000 | K16: 210000000 | L16: 210000000 | M16: 210000000 | N16: 210000000 | O16: 210000000 | P16: 210000000 | Q16: =SUM(E16:P16) -> 2520000000 | R16: =IFERROR(INDEX(Listas!$J$5:$J$11,MATCH(D16,Listas!$H$5:$H$11,0)),"Cuenta no encontrada") -> Gastos de administración
A17: FN_AUTOS | B17: CC_VENTAS | C17: CB_AUTOS | D17: 5205_SALARIOS_VENTAS | E17: 620000000 | F17: 620000000 | G17: 620000000 | H17: 620000000 | I17: 620000000 | J17: 620000000 | K17: 651000000 | L17: 651000000 | M17: 651000000 | N17: 651000000 | O17: 651000000 | P17: 651000000 | Q17: =SUM(E17:P17) -> 7626000000 | R17: =IFERROR(INDEX(Listas!$J$5:$J$11,MATCH(D17,Listas!$H$5:$H$11,0)),"Cuenta no encontrada") -> Gastos de ventas
A18: FN_AUTOS | B18: CC_VENTAS | C18: CB_AUTOS | D18: 5235_PUBLICIDAD | E18: 432000000 | F18: 480000000 | G18: 528000000 | H18: 432000000 | I18: 480000000 | J18: 528000000 | K18: 432000000 | L18: 480000000 | M18: 528000000 | N18: 432000000 | O18: 480000000 | P18: 528000000 | Q18: =SUM(E18:P18) -> 5760000000 | R18: =IFERROR(INDEX(Listas!$J$5:$J$11,MATCH(D18,Listas!$H$5:$H$11,0)),"Cuenta no encontrada") -> Gastos de ventas
A19: FN_TUBOS | B19: CC_PLANTA | C19: CB_TUBERIA | D19: 5105_SALARIOS | E19: 1300000000 | F19: 1300000000 | G19: 1300000000 | H19: 1300000000 | I19: 1300000000 | J19: 1300000000 | K19: 1365000000 | L19: 1365000000 | M19: 1365000000 | N19: 1365000000 | O19: 1365000000 | P19: 2015000000 | Q19: =SUM(E19:P19) -> 16640000000 | R19: =IFERROR(INDEX(Listas!$J$5:$J$11,MATCH(D19,Listas!$H$5:$H$11,0)),"Cuenta no encontrada") -> Gastos de administración
A20: FN_TUBOS | B20: CC_PLANTA | C20: CB_TUBERIA | D20: 5135_SERVICIOS | E20: 412800000 | F20: 430000000 | G20: 447200000 | H20: 412800000 | I20: 430000000 | J20: 447200000 | K20: 412800000 | L20: 430000000 | M20: 447200000 | N20: 412800000 | O20: 430000000 | P20: 447200000 | Q20: =SUM(E20:P20) -> 5160000000 | R20: =IFERROR(INDEX(Listas!$J$5:$J$11,MATCH(D20,Listas!$H$5:$H$11,0)),"Cuenta no encontrada") -> Gastos de administración
A21: FN_TUBOS | B21: CC_PLANTA | C21: CB_TUBERIA | D21: 5145_MANTENIMIENTO | E21: 254800000 | F21: 260000000 | G21: 265200000 | H21: 254800000 | I21: 260000000 | J21: 265200000 | K21: 254800000 | L21: 260000000 | M21: 265200000 | N21: 254800000 | O21: 260000000 | P21: 265200000 | Q21: =SUM(E21:P21) -> 3120000000 | R21: =IFERROR(INDEX(Listas!$J$5:$J$11,MATCH(D21,Listas!$H$5:$H$11,0)),"Cuenta no encontrada") -> Gastos de administración
... A23: FN_TUBOS | B23: CC_ADMIN | C23: CB_CORPORATIVO | D23: 5110_HONORARIOS | E23: 150000000 | F23: 150000000 | G23: 150000000 | H23: 150000000 | I23: 150000000 | J23: 150000000 | K23: 150000000 | L23: 150000000 | M23: 150000000 | N23: 150000000 | O23: 150000000 | P23: 150000000 | Q23: =SUM(E23:P23) -> 1800000000 | R23: =IFERROR(INDEX(Listas!$J$5:$J$11,MATCH(D23,Listas!$H$5:$H$11,0)),"Cuenta no encontrada") -> Gastos de administración
A24: Total gastos | E24: =SUM(E10:E23) -> 9743900000 | F24: =SUM(F10:F23) -> 9900000000 | G24: =SUM(G10:G23) -> 10056100000 | H24: =SUM(H10:H23) -> 9743900000 | I24: =SUM(I10:I23) -> 9900000000 | J24: =SUM(J10:J23) -> 10056100000 | K24: =SUM(K10:K23) -> 10064900000 | L24: =SUM(L10:L23) -> 10221000000 | ... Q24: =SUM(Q10:Q23) -> 123151000000
A26: Notas
A27: 1. La columna "Grupo P&L" sale de la propiedad de la cuenta (hoja Listas) y solo sirve para armar el P&L de este libro; no existe en la tabla del add-in.
A28: 2. La fila "Total gastos" es de control: en SAC los totales los calcula el modelo.
A29: 3. Diciembre incluye la prima de servicios en 5105_SALARIOS (+50 %).

Sheet Carga_EEFF
A1: Plantilla de carga: EEFF FANALCA (add-in de SAC para Excel)
A2: Balance proyectado en el formato del modelo EEFF: Cuentas_EF en filas, meses en columnas, COP. Pasivo y patrimonio con signo negativo (crédito), como en el modelo.
A3: Fuente de datos (add-in)
A4: Modelo | B4: Modelo EEFF FANALCA (C2kgen7fqc13vleoibl06hk4j7o)
A5: Versión | B5: public.Presupuesto_2026
A6: Sociedades | B6: FN_MOTOS
A7: Cebes | B7: CB_CORPORATIVO
A8: Auditoria | B8: CALCULADO_DA
A9: Moneda | B9: COP
A11: Cuentas_EF | B11: Descripción | C11: Tipo | D11: Ene 2026 | E11: Feb 2026 | F11: Mar 2026 | G11: Abr 2026 | H11: May 2026 | I11: Jun 2026 | J11: Jul 2026 | K11: Ago 2026 | L11: Sep 2026 | M11: Oct 2026 | N11: Nov 2026 | O11: Dic 2026
A12: 1105_CAJA | B12: Efectivo y equivalentes | C12: Activo | D12: =Balance!D6*Supuestos!$B$5 -> 4.4488223e+10 | E12: =Balance!E6*Supuestos!$B$5 -> 42291580000 | F12: =Balance!F6*Supuestos!$B$5 -> 3.4497401e+10 | G12: =Balance!G6*Supuestos!$B$5 -> 4.1312317e+10 | H12: =Balance!H6*Supuestos!$B$5 -> 4.1034593e+10 | I12: =Balance!I6*Supuestos!$B$5 -> 43551234000 | J12: =Balance!J6*Supuestos!$B$5 -> 50436295200 | K12: =Balance!K6*Supuestos!$B$5 -> 5.2021898e+10 | ... O12: =Balance!O6*Supuestos!$B$5 -> 6.2663969e+10
A13: 1305_CLIENTES | B13: Cuentas por cobrar clientes | C13: Activo | D13: =Balance!D7*Supuestos!$B$5 -> 81008400000 | E13: =Balance!E7*Supuestos!$B$5 -> 85048200000 | F13: =Balance!F7*Supuestos!$B$5 -> 95820150000 | G13: =Balance!G7*Supuestos!$B$5 -> 93807750000 | H13: =Balance!H7*Supuestos!$B$5 -> 98745000000 | I13: =Balance!I7*Supuestos!$B$5 -> 101669850000 | J13: =Balance!J7*Supuestos!$B$5 -> 100603080000 | K13: =Balance!K7*Supuestos!$B$5 -> 104788920000 | ... O13: =Balance!O7*Supuestos!$B$5 -> 121142280000
A14: 1435_INVENTARIOS | B14: Inventarios | C14: Activo | D14: =Balance!D8*Supuestos!$B$5 -> 73447616000 | E14: =Balance!E8*Supuestos!$B$5 -> 77110368000 | F14: =Balance!F8*Supuestos!$B$5 -> 86876936000 | G14: =Balance!G8*Supuestos!$B$5 -> 85052360000 | H14: =Balance!H8*Supuestos!$B$5 -> 89528800000 | I14: =Balance!I8*Supuestos!$B$5 -> 92180664000 | J14: =Balance!J8*Supuestos!$B$5 -> 91213459200 | K14: =Balance!K8*Supuestos!$B$5 -> 95008620800 | ... O14: =Balance!O8*Supuestos!$B$5 -> 109835667200
A15: 1520_PPE | B15: Propiedad, planta y equipo (bruto) | C15: Activo | D15: =Balance!D9*Supuestos!$B$5 -> 423000000000 | E15: =Balance!E9*Supuestos!$B$5 -> 426000000000 | F15: =Balance!F9*Supuestos!$B$5 -> 429000000000 | G15: =Balance!G9*Supuestos!$B$5 -> 432000000000 | H15: =Balance!H9*Supuestos!$B$5 -> 435000000000 | I15: =Balance!I9*Supuestos!$B$5 -> 438000000000 | J15: =Balance!J9*Supuestos!$B$5 -> 441000000000 | K15: =Balance!K9*Supuestos!$B$5 -> 444000000000 | ... O15: =Balance!O9*Supuestos!$B$5 -> 456000000000
A16: 1592_DEP_ACUMULADA | B16: Depreciación acumulada | C16: Activo | D16: =Balance!D10*Supuestos!$B$5 -> -153525000000 | E16: =Balance!E10*Supuestos!$B$5 -> -157075000000 | F16: =Balance!F10*Supuestos!$B$5 -> -160650000000 | G16: =Balance!G10*Supuestos!$B$5 -> -164250000000 | H16: =Balance!H10*Supuestos!$B$5 -> -167875000000 | I16: =Balance!I10*Supuestos!$B$5 -> -171525000000 | J16: =Balance!J10*Supuestos!$B$5 -> -175200000000 | K16: =Balance!K10*Supuestos!$B$5 -> -178900000000 | ... O16: =Balance!O10*Supuestos!$B$5 -> -193950000000
A17: 2105_OBLIGACIONES_FIN | B17: Obligaciones financieras | C17: Pasivo | D17: =-Balance!D14*Supuestos!$B$5 -> -179000000000 | E17: =-Balance!E14*Supuestos!$B$5 -> -178000000000 | F17: =-Balance!F14*Supuestos!$B$5 -> -177000000000 | G17: =-Balance!G14*Supuestos!$B$5 -> -176000000000 | H17: =-Balance!H14*Supuestos!$B$5 -> -175000000000 | I17: =-Balance!I14*Supuestos!$B$5 -> -174000000000 | J17: =-Balance!J14*Supuestos!$B$5 -> -173000000000 | K17: =-Balance!K14*Supuestos!$B$5 -> -172000000000 | ... O17: =-Balance!O14*Supuestos!$B$5 -> -168000000000
A18: 2205_PROVEEDORES | B18: Proveedores | C18: Pasivo | D18: =-Balance!D15*Supuestos!$B$5 -> -6.1206347e+10 | E18: =-Balance!E15*Supuestos!$B$5 -> -64258640000 | F18: =-Balance!F15*Supuestos!$B$5 -> -7.2397447e+10 | G18: =-Balance!G15*Supuestos!$B$5 -> -7.0876967e+10 | H18: =-Balance!H15*Supuestos!$B$5 -> -7.4607333e+10 | I18: =-Balance!I15*Supuestos!$B$5 -> -76817220000 | J18: =-Balance!J15*Supuestos!$B$5 -> -76011216000 | K18: =-Balance!K15*Supuestos!$B$5 -> -7.9173851e+10 | ... O18: =-Balance!O15*Supuestos!$B$5 -> -9.1529723e+10
A19: 2404_IMPUESTO_RENTA | B19: Impuesto de renta por pagar | C19: Pasivo | D19: =-Balance!D16*Supuestos!$B$5 -> -7.745122e+08 | E19: =-Balance!E16*Supuestos!$B$5 -> -1790777800 | F19: =-Balance!F16*Supuestos!$B$5 -> -3.551464e+09 | G19: =-Balance!G16*Supuestos!$B$5 -> -5.265911e+09 | H19: =-Balance!H16*Supuestos!$B$5 -> -7.289121e+09 | I19: =-Balance!I16*Supuestos!$B$5 -> -9.4708348e+09 | J19: =-Balance!J16*Supuestos!$B$5 -> -11564566440 | K19: =-Balance!K16*Supuestos!$B$5 -> -13910955800 | ... O19: =-Balance!O16*Supuestos!$B$5 -> -24556767760
A20: 3105_CAPITAL | B20: Capital suscrito y pagado | C20: Patrimonio | D20: =-Balance!D20*Supuestos!$B$5 -> -200000000000 | E20: =-Balance!E20*Supuestos!$B$5 -> -200000000000 | F20: =-Balance!F20*Supuestos!$B$5 -> -200000000000 | G20: =-Balance!G20*Supuestos!$B$5 -> -200000000000 | H20: =-Balance!H20*Supuestos!$B$5 -> -200000000000 | I20: =-Balance!I20*Supuestos!$B$5 -> -200000000000 | J20: =-Balance!J20*Supuestos!$B$5 -> -200000000000 | K20: =-Balance!K20*Supuestos!$B$5 -> -200000000000 | ... O20: =-Balance!O20*Supuestos!$B$5 -> -200000000000
A21: 3705_UTILIDADES_ACUM | B21: Utilidades acumuladas | C21: Patrimonio | D21: =-Balance!D21*Supuestos!$B$5 -> -26000000000 | E21: =-Balance!E21*Supuestos!$B$5 -> -26000000000 | F21: =-Balance!F21*Supuestos!$B$5 -> -26000000000 | G21: =-Balance!G21*Supuestos!$B$5 -> -26000000000 | H21: =-Balance!H21*Supuestos!$B$5 -> -26000000000 | I21: =-Balance!I21*Supuestos!$B$5 -> -26000000000 | J21: =-Balance!J21*Supuestos!$B$5 -> -26000000000 | K21: =-Balance!K21*Supuestos!$B$5 -> -26000000000 | ... O21: =-Balance!O21*Supuestos!$B$5 -> -26000000000
A22: 3605_UTILIDAD_EJERCICIO | B22: Utilidad del ejercicio | C22: Patrimonio | D22: =-Balance!D22*Supuestos!$B$5 -> -1438379800 | E22: =-Balance!E22*Supuestos!$B$5 -> -3.3257302e+09 | F22: =-Balance!F22*Supuestos!$B$5 -> -6.595576e+09 | G22: =-Balance!G22*Supuestos!$B$5 -> -9.779549e+09 | H22: =-Balance!H22*Supuestos!$B$5 -> -13536939000 | I22: =-Balance!I22*Supuestos!$B$5 -> -17588693200 | J22: =-Balance!J22*Supuestos!$B$5 -> -21477051960 | K22: =-Balance!K22*Supuestos!$B$5 -> -25834632200 | ... O22: =-Balance!O22*Supuestos!$B$5 -> -45605425840
A23: Control: suma debe ser 0 | D23: =ROUND(SUM(D12:D22),0) -> 0 | E23: =ROUND(SUM(E12:E22),0) -> 0 | F23: =ROUND(SUM(F12:F22),0) -> 0 | G23: =ROUND(SUM(G12:G22),0) -> 0 | H23: =ROUND(SUM(H12:H22),0) -> 0 | I23: =ROUND(SUM(I12:I22),0) -> 0 | J23: =ROUND(SUM(J12:J22),0) -> 0 | K23: =ROUND(SUM(K12:K22),0) -> 0 | ... O23: =ROUND(SUM(O12:O22),0) -> 0
A25: Notas
A26: 1. Los valores (texto verde) vienen de la hoja Balance: copie y pegue como valores en la tabla del add-in conectada al modelo EEFF.
A27: 2. Ajuste Sociedades y Cebes del encabezado al miembro donde se registra el consolidado en su modelo.
A28: 3. Si el modelo EEFF calcula la utilidad del ejercicio con un data action, no publique la fila 3605.

Sheet Carga_Plana
A1: Formato plano: botón de carga de archivos (data upload starter) o Cargador de datos a SAC
A2: Una fila por combinación y mes, con la medida en una sola columna. Los encabezados deben coincidir con los de la plantilla del trabajo de carga en SAC.
A4: Date | B4: Sociedades | C4: Cebes | D4: Clientes | E4: Referencias | F4: Ratio | G4: Auditoria | H4: Moneda | I4: Importe
A5: 202601 | B5: FN_MOTOS | C5: CB_MOTOS | D5: CLI_001 | E5: REF_CB125 | F5: UNIDADES | G5: PRESUPUESTO_EXCEL | H5: COP | I5: =Carga_Ingresos!F10 -> 1640
A6: 202601 | B6: FN_MOTOS | C6: CB_MOTOS | D6: CLI_001 | E6: REF_CB125 | F6: PRECIO | G6: PRESUPUESTO_EXCEL | H6: COP | I6: =Carga_Ingresos!F11 -> 9890000
A7: 202602 | B7: FN_MOTOS | C7: CB_MOTOS | D7: CLI_001 | E7: REF_CB125 | F7: UNIDADES | G7: PRESUPUESTO_EXCEL | H7: COP | I7: =Carga_Ingresos!G10 -> 1720
A8: 202602 | B8: FN_MOTOS | C8: CB_MOTOS | D8: CLI_001 | E8: REF_CB125 | F8: PRECIO | G8: PRESUPUESTO_EXCEL | H8: COP | I8: =Carga_Ingresos!G11 -> 9890000
A9: 202601 | B9: FN_MOTOS | C9: CB_MOTOS | D9: CLI_003 | E9: REF_XR190 | F9: UNIDADES | G9: PRESUPUESTO_EXCEL | H9: COP | I9: =Carga_Ingresos!F13 -> 738
A10: 202601 | B10: FN_MOTOS | C10: CB_MOTOS | D10: CLI_003 | E10: REF_XR190 | F10: PRECIO | G10: PRESUPUESTO_EXCEL | H10: COP | I10: =Carga_Ingresos!F14 -> 14500000
A11: 202602 | B11: FN_MOTOS | C11: CB_MOTOS | D11: CLI_003 | E11: REF_XR190 | F11: UNIDADES | G11: PRESUPUESTO_EXCEL | H11: COP | I11: =Carga_Ingresos!G13 -> 774
A12: 202602 | B12: FN_MOTOS | C12: CB_MOTOS | D12: CLI_003 | E12: REF_XR190 | F12: PRECIO | G12: PRESUPUESTO_EXCEL | H12: COP | I12: =Carga_Ingresos!G14 -> 14500000
A13: 202601 | B13: FN_AUTOS | C13: CB_AUTOS | D13: CLI_004 | E13: REF_CIVIC | F13: UNIDADES | G13: PRESUPUESTO_EXCEL | H13: COP | I13: =Carga_Ingresos!F16 -> 49
A14: 202601 | B14: FN_AUTOS | C14: CB_AUTOS | D14: CLI_004 | E14: REF_CIVIC | F14: PRECIO | G14: PRESUPUESTO_EXCEL | H14: COP | I14: =Carga_Ingresos!F17 -> 145000000
A15: 202602 | B15: FN_AUTOS | C15: CB_AUTOS | D15: CLI_004 | E15: REF_CIVIC | F15: UNIDADES | G15: PRESUPUESTO_EXCEL | H15: COP | I15: =Carga_Ingresos!G16 -> 52
A16: 202602 | B16: FN_AUTOS | C16: CB_AUTOS | D16: CLI_004 | E16: REF_CIVIC | F16: PRECIO | G16: PRESUPUESTO_EXCEL | H16: COP | I16: =Carga_Ingresos!G17 -> 145000000
A18: Notas
A19: 1. Date en formato AAAAMM como texto (202601). La versión no va en el archivo: se elige al cargar.
A20: 2. Los importes (verde) se toman de Carga_Ingresos para el ejemplo; en un archivo real van como valores.
A21: 3. El botón de carga de SAC exige las mismas columnas y encabezados que el archivo de muestra con que el modelador creó el trabajo de carga.
A22: 4. Este mismo formato lo acepta el Cargador de datos a SAC (encabezados = nombres de las dimensiones).

Sheet PyG
A1: Estado de resultados (P&L) 2026 – FANALCA consolidado
A2: Millones de COP. Ingresos y gastos vienen de las plantillas de carga; costo, depreciación, intereses e impuesto de la hoja Supuestos.
A4: Código | B4: Concepto | D4: Ene 2026 | E4: Feb 2026 | F4: Mar 2026 | G4: Abr 2026 | H4: May 2026 | I4: Jun 2026 | J4: Jul 2026 | K4: Ago 2026 | L4: Sep 2026 | M4: Oct 2026 | N4: Nov 2026 | O4: Dic 2026 | P4: Total 2026
B5: Ingresos operacionales
A6: FN_MOTOS | B6: Ventas Motos | D6: =SUMIFS(Carga_Ingresos!F$10:F$27,Carga_Ingresos!$A$10:$A$27,"FN_MOTOS",Carga_Ingresos!$E$10:$E$27,"ING_VENTAS_NAL")/Supuestos!$B$5 -> 26920.6 | E6: =SUMIFS(Carga_Ingresos!G$10:G$27,Carga_Ingresos!$A$10:$A$27,"FN_MOTOS",Carga_Ingresos!$E$10:$E$27,"ING_VENTAS_NAL")/Supuestos!$B$5 -> 28233.8 | F6: =SUMIFS(Carga_Ingresos!H$10:H$27,Carga_Ingresos!$A$10:$A$27,"FN_MOTOS",Carga_Ingresos!$E$10:$E$27,"ING_VENTAS_NAL")/Supuestos!$B$5 -> 31845.1 | G6: =SUMIFS(Carga_Ingresos!I$10:I$27,Carga_Ingresos!$A$10:$A$27,"FN_MOTOS",Carga_Ingresos!$E$10:$E$27,"ING_VENTAS_NAL")/Supuestos!$B$5 -> 31188.5 | H6: =SUMIFS(Carga_Ingresos!J$10:J$27,Carga_Ingresos!$A$10:$A$27,"FN_MOTOS",Carga_Ingresos!$E$10:$E$27,"ING_VENTAS_NAL")/Supuestos!$B$5 -> 32830 | I6: =SUMIFS(Carga_Ingresos!K$10:K$27,Carga_Ingresos!$A$10:$A$27,"FN_MOTOS",Carga_Ingresos!$E$10:$E$27,"ING_VENTAS_NAL")/Supuestos!$B$5 -> 33814.9 | J6: =SUMIFS(Carga_Ingresos!L$10:L$27,Carga_Ingresos!$A$10:$A$27,"FN_MOTOS",Carga_Ingresos!$E$10:$E$27,"ING_VENTAS_NAL")/Supuestos!$B$5 -> 33461.12 | K6: =SUMIFS(Carga_Ingresos!M$10:M$27,Carga_Ingresos!$A$10:$A$27,"FN_MOTOS",Carga_Ingresos!$E$10:$E$27,"ING_VENTAS_NAL")/Supuestos!$B$5 -> 34826.88 | ... O6: =SUMIFS(Carga_Ingresos!Q$10:Q$27,Carga_Ingresos!$A$10:$A$27,"FN_MOTOS",Carga_Ingresos!$E$10:$E$27,"ING_VENTAS_NAL")/Supuestos!$B$5 -> 40289.92 | P6: =SUM(D6:O6) -> 402330.18
A7: FN_AUTOS | B7: Ventas Autos | D7: =SUMIFS(Carga_Ingresos!F$10:F$27,Carga_Ingresos!$A$10:$A$27,"FN_AUTOS",Carga_Ingresos!$E$10:$E$27,"ING_VENTAS_NAL")/Supuestos!$B$5 -> 16015 | E7: =SUMIFS(Carga_Ingresos!G$10:G$27,Carga_Ingresos!$A$10:$A$27,"FN_AUTOS",Carga_Ingresos!$E$10:$E$27,"ING_VENTAS_NAL")/Supuestos!$B$5 -> 16855 | F7: =SUMIFS(Carga_Ingresos!H$10:H$27,Carga_Ingresos!$A$10:$A$27,"FN_AUTOS",Carga_Ingresos!$E$10:$E$27,"ING_VENTAS_NAL")/Supuestos!$B$5 -> 18940 | G7: =SUMIFS(Carga_Ingresos!I$10:I$27,Carga_Ingresos!$A$10:$A$27,"FN_AUTOS",Carga_Ingresos!$E$10:$E$27,"ING_VENTAS_NAL")/Supuestos!$B$5 -> 18525 | H7: =SUMIFS(Carga_Ingresos!J$10:J$27,Carga_Ingresos!$A$10:$A$27,"FN_AUTOS",Carga_Ingresos!$E$10:$E$27,"ING_VENTAS_NAL")/Supuestos!$B$5 -> 19500 | I7: =SUMIFS(Carga_Ingresos!K$10:K$27,Carga_Ingresos!$A$10:$A$27,"FN_AUTOS",Carga_Ingresos!$E$10:$E$27,"ING_VENTAS_NAL")/Supuestos!$B$5 -> 20060 | J7: =SUMIFS(Carga_Ingresos!L$10:L$27,Carga_Ingresos!$A$10:$A$27,"FN_AUTOS",Carga_Ingresos!$E$10:$E$27,"ING_VENTAS_NAL")/Supuestos!$B$5 -> 19848.4 | K7: =SUMIFS(Carga_Ingresos!M$10:M$27,Carga_Ingresos!$A$10:$A$27,"FN_AUTOS",Carga_Ingresos!$E$10:$E$27,"ING_VENTAS_NAL")/Supuestos!$B$5 -> 20711.6 | ... O7: =SUMIFS(Carga_Ingresos!Q$10:Q$27,Carga_Ingresos!$A$10:$A$27,"FN_AUTOS",Carga_Ingresos!$E$10:$E$27,"ING_VENTAS_NAL")/Supuestos!$B$5 -> 23904.4 | P7: =SUM(D7:O7) -> 239115
A8: FN_TUBOS | B8: Ventas Tubos | D8: =SUMIFS(Carga_Ingresos!F$10:F$27,Carga_Ingresos!$A$10:$A$27,"FN_TUBOS",Carga_Ingresos!$E$10:$E$27,"ING_VENTAS_NAL")/Supuestos!$B$5 -> 11070 | E8: =SUMIFS(Carga_Ingresos!G$10:G$27,Carga_Ingresos!$A$10:$A$27,"FN_TUBOS",Carga_Ingresos!$E$10:$E$27,"ING_VENTAS_NAL")/Supuestos!$B$5 -> 11610 | F8: =SUMIFS(Carga_Ingresos!H$10:H$27,Carga_Ingresos!$A$10:$A$27,"FN_TUBOS",Carga_Ingresos!$E$10:$E$27,"ING_VENTAS_NAL")/Supuestos!$B$5 -> 13095 | G8: =SUMIFS(Carga_Ingresos!I$10:I$27,Carga_Ingresos!$A$10:$A$27,"FN_TUBOS",Carga_Ingresos!$E$10:$E$27,"ING_VENTAS_NAL")/Supuestos!$B$5 -> 12825 | H8: =SUMIFS(Carga_Ingresos!J$10:J$27,Carga_Ingresos!$A$10:$A$27,"FN_TUBOS",Carga_Ingresos!$E$10:$E$27,"ING_VENTAS_NAL")/Supuestos!$B$5 -> 13500 | I8: =SUMIFS(Carga_Ingresos!K$10:K$27,Carga_Ingresos!$A$10:$A$27,"FN_TUBOS",Carga_Ingresos!$E$10:$E$27,"ING_VENTAS_NAL")/Supuestos!$B$5 -> 13905 | J8: =SUMIFS(Carga_Ingresos!L$10:L$27,Carga_Ingresos!$A$10:$A$27,"FN_TUBOS",Carga_Ingresos!$E$10:$E$27,"ING_VENTAS_NAL")/Supuestos!$B$5 -> 13759.2 | K8: =SUMIFS(Carga_Ingresos!M$10:M$27,Carga_Ingresos!$A$10:$A$27,"FN_TUBOS",Carga_Ingresos!$E$10:$E$27,"ING_VENTAS_NAL")/Supuestos!$B$5 -> 14320.8 | ... O8: =SUMIFS(Carga_Ingresos!Q$10:Q$27,Carga_Ingresos!$A$10:$A$27,"FN_TUBOS",Carga_Ingresos!$E$10:$E$27,"ING_VENTAS_NAL")/Supuestos!$B$5 -> 16567.2 | P8: =SUM(D8:O8) -> 165439.8
A9: 41 | B9: Total ingresos | D9: =SUM(D6:D8) -> 54005.6 | E9: =SUM(E6:E8) -> 56698.8 | F9: =SUM(F6:F8) -> 63880.1 | G9: =SUM(G6:G8) -> 62538.5 | H9: =SUM(H6:H8) -> 65830 | I9: =SUM(I6:I8) -> 67779.9 | J9: =SUM(J6:J8) -> 67068.72 | K9: =SUM(K6:K8) -> 69859.28 | ... O9: =SUM(O6:O8) -> 80761.52 | P9: =SUM(D9:O9) -> 806884.98
A10: 61 | B10: Costo de ventas | D10: =-D9*Supuestos!$B$6 -> -36723.808 | E10: =-E9*Supuestos!$B$6 -> -38555.184 | F10: =-F9*Supuestos!$B$6 -> -43438.468 | G10: =-G9*Supuestos!$B$6 -> -42526.18 | H10: =-H9*Supuestos!$B$6 -> -44764.4 | I10: =-I9*Supuestos!$B$6 -> -46090.332 | J10: =-J9*Supuestos!$B$6 -> -45606.73 | K10: =-K9*Supuestos!$B$6 -> -47504.31 | ... O10: =-O9*Supuestos!$B$6 -> -54917.834 | P10: =SUM(D10:O10) -> -548681.79
B11: Utilidad bruta | D11: =D9+D10 -> 17281.792 | E11: =E9+E10 -> 18143.616 | F11: =F9+F10 -> 20441.632 | G11: =G9+G10 -> 20012.32 | H11: =H9+H10 -> 21065.6 | I11: =I9+I10 -> 21689.568 | J11: =J9+J10 -> 21461.99 | K11: =K9+K10 -> 22354.97 | ... O11: =O9+O10 -> 25843.686 | P11: =SUM(D11:O11) -> 258203.19
B12: Margen bruto | D12: =IFERROR(D11/D9,0) -> 0.32 | E12: =IFERROR(E11/E9,0) -> 0.32 | F12: =IFERROR(F11/F9,0) -> 0.32 | G12: =IFERROR(G11/G9,0) -> 0.32 | H12: =IFERROR(H11/H9,0) -> 0.32 | I12: =IFERROR(I11/I9,0) -> 0.32 | J12: =IFERROR(J11/J9,0) -> 0.32 | K12: =IFERROR(K11/K9,0) -> 0.32 | ... P12: =IFERROR(P11/P9,0) -> 0.32
B14: Gastos operacionales
A15: 51 | B15: Gastos de administración | D15: =-SUMIFS(Carga_Gastos!E$10:E$23,Carga_Gastos!$R$10:$R$23,"Gastos de administración")/Supuestos!$B$5 -> -6250 | E15: =-SUMIFS(Carga_Gastos!F$10:F$23,Carga_Gastos!$R$10:$R$23,"Gastos de administración")/Supuestos!$B$5 -> -6280 | F15: =-SUMIFS(Carga_Gastos!G$10:G$23,Carga_Gastos!$R$10:$R$23,"Gastos de administración")/Supuestos!$B$5 -> -6310 | G15: =-SUMIFS(Carga_Gastos!H$10:H$23,Carga_Gastos!$R$10:$R$23,"Gastos de administración")/Supuestos!$B$5 -> -6250 | H15: =-SUMIFS(Carga_Gastos!I$10:I$23,Carga_Gastos!$R$10:$R$23,"Gastos de administración")/Supuestos!$B$5 -> -6280 | I15: =-SUMIFS(Carga_Gastos!J$10:J$23,Carga_Gastos!$R$10:$R$23,"Gastos de administración")/Supuestos!$B$5 -> -6310 | J15: =-SUMIFS(Carga_Gastos!K$10:K$23,Carga_Gastos!$R$10:$R$23,"Gastos de administración")/Supuestos!$B$5 -> -6492.5 | K15: =-SUMIFS(Carga_Gastos!L$10:L$23,Carga_Gastos!$R$10:$R$23,"Gastos de administración")/Supuestos!$B$5 -> -6522.5 | ... O15: =-SUMIFS(Carga_Gastos!P$10:P$23,Carga_Gastos!$R$10:$R$23,"Gastos de administración")/Supuestos!$B$5 -> -8977.5 | P15: =SUM(D15:O15) -> -79240
A16: 52 | B16: Gastos de ventas | D16: =-SUMIFS(Carga_Gastos!E$10:E$23,Carga_Gastos!$R$10:$R$23,"Gastos de ventas")/Supuestos!$B$5 -> -3493.9 | E16: =-SUMIFS(Carga_Gastos!F$10:F$23,Carga_Gastos!$R$10:$R$23,"Gastos de ventas")/Supuestos!$B$5 -> -3620 | F16: =-SUMIFS(Carga_Gastos!G$10:G$23,Carga_Gastos!$R$10:$R$23,"Gastos de ventas")/Supuestos!$B$5 -> -3746.1 | G16: =-SUMIFS(Carga_Gastos!H$10:H$23,Carga_Gastos!$R$10:$R$23,"Gastos de ventas")/Supuestos!$B$5 -> -3493.9 | H16: =-SUMIFS(Carga_Gastos!I$10:I$23,Carga_Gastos!$R$10:$R$23,"Gastos de ventas")/Supuestos!$B$5 -> -3620 | I16: =-SUMIFS(Carga_Gastos!J$10:J$23,Carga_Gastos!$R$10:$R$23,"Gastos de ventas")/Supuestos!$B$5 -> -3746.1 | J16: =-SUMIFS(Carga_Gastos!K$10:K$23,Carga_Gastos!$R$10:$R$23,"Gastos de ventas")/Supuestos!$B$5 -> -3572.4 | K16: =-SUMIFS(Carga_Gastos!L$10:L$23,Carga_Gastos!$R$10:$R$23,"Gastos de ventas")/Supuestos!$B$5 -> -3698.5 | ... O16: =-SUMIFS(Carga_Gastos!P$10:P$23,Carga_Gastos!$R$10:$R$23,"Gastos de ventas")/Supuestos!$B$5 -> -3824.6 | P16: =SUM(D16:O16) -> -43911
B17: EBITDA | D17: =D11+D15+D16 -> 7537.892 | E17: =E11+E15+E16 -> 8243.616 | F17: =F11+F15+F16 -> 10385.532 | G17: =G11+G15+G16 -> 10268.42 | H17: =H11+H15+H16 -> 11165.6 | I17: =I11+I15+I16 -> 11633.468 | J17: =J11+J15+J16 -> 11397.09 | K17: =K11+K15+K16 -> 12133.97 | ... O17: =O11+O15+O16 -> 13041.586 | P17: =SUM(D17:O17) -> 135052.19
B18: Margen EBITDA | D18: =IFERROR(D17/D9,0) -> 0.13957612 | E18: =IFERROR(E17/E9,0) -> 0.14539313 | F18: =IFERROR(F17/F9,0) -> 0.16257852 | G18: =IFERROR(G17/G9,0) -> 0.16419358 | H18: =IFERROR(H17/H9,0) -> 0.16961264 | I18: =IFERROR(I17/I9,0) -> 0.17163596 | J18: =IFERROR(J17/J9,0) -> 0.16993153 | K18: =IFERROR(K17/K9,0) -> 0.17369159 | ... P18: =IFERROR(P17/P9,0) -> 0.16737478
A19: 5160 | B19: Depreciación | D19: =-Balance!D9/(Supuestos!$B$12*12) -> -3525 | E19: =-Balance!E9/(Supuestos!$B$12*12) -> -3550 | F19: =-Balance!F9/(Supuestos!$B$12*12) -> -3575 | G19: =-Balance!G9/(Supuestos!$B$12*12) -> -3600 | H19: =-Balance!H9/(Supuestos!$B$12*12) -> -3625 | I19: =-Balance!I9/(Supuestos!$B$12*12) -> -3650 | J19: =-Balance!J9/(Supuestos!$B$12*12) -> -3675 | K19: =-Balance!K9/(Supuestos!$B$12*12) -> -3700 | ... O19: =-Balance!O9/(Supuestos!$B$12*12) -> -3800 | P19: =SUM(D19:O19) -> -43950
B20: Utilidad operacional (EBIT) | D20: =D17+D19 -> 4012.892 | E20: =E17+E19 -> 4693.616 | F20: =F17+F19 -> 6810.532 | G20: =G17+G19 -> 6668.42 | H20: =H17+H19 -> 7540.6 | I20: =I17+I19 -> 7983.468 | J20: =J17+J19 -> 7722.0904 | K20: =K17+K19 -> 8433.9696 | ... O20: =O17+O19 -> 9241.5864 | P20: =SUM(D20:O20) -> 91102.194
A21: 5305 | B21: Gastos financieros (intereses) | D21: =-Balance!C14*Supuestos!$B$13/12 -> -1800 | E21: =-Balance!D14*Supuestos!$B$13/12 -> -1790 | F21: =-Balance!E14*Supuestos!$B$13/12 -> -1780 | G21: =-Balance!F14*Supuestos!$B$13/12 -> -1770 | H21: =-Balance!G14*Supuestos!$B$13/12 -> -1760 | I21: =-Balance!H14*Supuestos!$B$13/12 -> -1750 | J21: =-Balance!I14*Supuestos!$B$13/12 -> -1740 | K21: =-Balance!J14*Supuestos!$B$13/12 -> -1730 | ... O21: =-Balance!N14*Supuestos!$B$13/12 -> -1690 | P21: =SUM(D21:O21) -> -20940
B22: Utilidad antes de impuestos | D22: =D20+D21 -> 2212.892 | E22: =E20+E21 -> 2903.616 | F22: =F20+F21 -> 5030.532 | G22: =G20+G21 -> 4898.42 | H22: =H20+H21 -> 5780.6 | I22: =I20+I21 -> 6233.468 | J22: =J20+J21 -> 5982.0904 | K22: =K20+K21 -> 6703.9696 | ... O22: =O20+O21 -> 7551.5864 | P22: =SUM(D22:O22) -> 70162.194
A23: 5405 | B23: Impuesto de renta | D23: =-MAX(0,D22)*Supuestos!$B$7 -> -774.5122 | E23: =-MAX(0,E22)*Supuestos!$B$7 -> -1016.2656 | F23: =-MAX(0,F22)*Supuestos!$B$7 -> -1760.6862 | G23: =-MAX(0,G22)*Supuestos!$B$7 -> -1714.447 | H23: =-MAX(0,H22)*Supuestos!$B$7 -> -2023.21 | I23: =-MAX(0,I22)*Supuestos!$B$7 -> -2181.7138 | J23: =-MAX(0,J22)*Supuestos!$B$7 -> -2093.7316 | K23: =-MAX(0,K22)*Supuestos!$B$7 -> -2346.3894 | ... O23: =-MAX(0,O22)*Supuestos!$B$7 -> -2643.0552 | P23: =SUM(D23:O23) -> -24556.768
B24: Utilidad neta | D24: =D22+D23 -> 1438.3798 | E24: =E22+E23 -> 1887.3504 | F24: =F22+F23 -> 3269.8458 | G24: =G22+G23 -> 3183.973 | H24: =H22+H23 -> 3757.39 | I24: =I22+I23 -> 4051.7542 | J24: =J22+J23 -> 3888.3588 | K24: =K22+K23 -> 4357.5802 | ... O24: =O22+O23 -> 4908.5312 | P24: =SUM(D24:O24) -> 45605.426
B25: Margen neto | D25: =IFERROR(D24/D9,0) -> 0.026633901 | E25: =IFERROR(E24/E9,0) -> 0.033287308 | F25: =IFERROR(F24/F9,0) -> 0.051187237 | G25: =IFERROR(G24/G9,0) -> 0.050912206 | H25: =IFERROR(H24/H9,0) -> 0.057077168 | I25: =IFERROR(I24/I9,0) -> 0.059778108 | J25: =IFERROR(J24/J9,0) -> 0.057975741 | K25: =IFERROR(K24/K9,0) -> 0.062376541 | ... P25: =IFERROR(P24/P9,0) -> 0.056520355

Sheet Balance
A1: Balance general 2026 – FANALCA consolidado
A2: Millones de COP, saldos al cierre de cada mes. La caja viene del flujo de caja; las demás cuentas de los supuestos de capital de trabajo, inversión y deuda.
A4: Código | B4: Concepto | C4: Dic 2025 | D4: Ene 2026 | E4: Feb 2026 | F4: Mar 2026 | G4: Abr 2026 | H4: May 2026 | I4: Jun 2026 | J4: Jul 2026 | K4: Ago 2026 | L4: Sep 2026 | M4: Oct 2026 | N4: Nov 2026 | O4: Dic 2026 | P4: Total 2026
B5: Activo
A6: 1105_CAJA | B6: Efectivo y equivalentes | C6: =Supuestos!$B$18 -> 25000 | D6: =Flujo_Caja!D24 -> 44488.223 | E6: =Flujo_Caja!E24 -> 42291.58 | F6: =Flujo_Caja!F24 -> 34497.401 | G6: =Flujo_Caja!G24 -> 41312.317 | H6: =Flujo_Caja!H24 -> 41034.593 | I6: =Flujo_Caja!I24 -> 43551.234 | J6: =Flujo_Caja!J24 -> 50436.295 | K6: =Flujo_Caja!K24 -> 52021.898 | ... O6: =Flujo_Caja!O24 -> 62663.969 | P6: =O6 -> 62663.969
A7: 1305_CLIENTES | B7: Cuentas por cobrar clientes | C7: =Supuestos!$B$19 -> 98000 | D7: =PyG!D9*Supuestos!$B$8/30 -> 81008.4 | E7: =PyG!E9*Supuestos!$B$8/30 -> 85048.2 | F7: =PyG!F9*Supuestos!$B$8/30 -> 95820.15 | G7: =PyG!G9*Supuestos!$B$8/30 -> 93807.75 | H7: =PyG!H9*Supuestos!$B$8/30 -> 98745 | I7: =PyG!I9*Supuestos!$B$8/30 -> 101669.85 | J7: =PyG!J9*Supuestos!$B$8/30 -> 100603.08 | K7: =PyG!K9*Supuestos!$B$8/30 -> 104788.92 | ... O7: =PyG!O9*Supuestos!$B$8/30 -> 121142.28 | P7: =O7 -> 121142.28
A8: 1435_INVENTARIOS | B8: Inventarios | C8: =Supuestos!$B$20 -> 76000 | D8: =-PyG!D10*Supuestos!$B$9/30 -> 73447.616 | E8: =-PyG!E10*Supuestos!$B$9/30 -> 77110.368 | F8: =-PyG!F10*Supuestos!$B$9/30 -> 86876.936 | G8: =-PyG!G10*Supuestos!$B$9/30 -> 85052.36 | H8: =-PyG!H10*Supuestos!$B$9/30 -> 89528.8 | I8: =-PyG!I10*Supuestos!$B$9/30 -> 92180.664 | J8: =-PyG!J10*Supuestos!$B$9/30 -> 91213.459 | K8: =-PyG!K10*Supuestos!$B$9/30 -> 95008.621 | ... O8: =-PyG!O10*Supuestos!$B$9/30 -> 109835.67 | P8: =O8 -> 109835.67
A9: 1520_PPE | B9: Propiedad, planta y equipo (bruto) | C9: =Supuestos!$B$21 -> 420000 | D9: =C9+Supuestos!$B$11 -> 423000 | E9: =D9+Supuestos!$B$11 -> 426000 | F9: =E9+Supuestos!$B$11 -> 429000 | G9: =F9+Supuestos!$B$11 -> 432000 | H9: =G9+Supuestos!$B$11 -> 435000 | I9: =H9+Supuestos!$B$11 -> 438000 | J9: =I9+Supuestos!$B$11 -> 441000 | K9: =J9+Supuestos!$B$11 -> 444000 | ... O9: =N9+Supuestos!$B$11 -> 456000 | P9: =O9 -> 456000
A10: 1592_DEP_ACUMULADA | B10: Depreciación acumulada | C10: =Supuestos!$B$22 -> -150000 | D10: =C10+PyG!D19 -> -153525 | E10: =D10+PyG!E19 -> -157075 | F10: =E10+PyG!F19 -> -160650 | G10: =F10+PyG!G19 -> -164250 | H10: =G10+PyG!H19 -> -167875 | I10: =H10+PyG!I19 -> -171525 | J10: =I10+PyG!J19 -> -175200 | K10: =J10+PyG!K19 -> -178900 | ... O10: =N10+PyG!O19 -> -193950 | P10: =O10 -> -193950
B11: Total activo | C11: =SUM(C6:C10) -> 469000 | D11: =SUM(D6:D10) -> 468419.24 | E11: =SUM(E6:E10) -> 473375.15 | F11: =SUM(F6:F10) -> 485544.49 | G11: =SUM(G6:G10) -> 487922.43 | H11: =SUM(H6:H10) -> 496433.39 | I11: =SUM(I6:I10) -> 503876.75 | J11: =SUM(J6:J10) -> 508052.83 | ... O11: =SUM(O6:O10) -> 555691.92 | P11: =O11 -> 555691.92
B13: Pasivo
A14: 2105_OBLIGACIONES_FIN | B14: Obligaciones financieras | C14: =Supuestos!$B$23 -> 180000 | D14: =MAX(0,C14-Supuestos!$B$14) -> 179000 | E14: =MAX(0,D14-Supuestos!$B$14) -> 178000 | F14: =MAX(0,E14-Supuestos!$B$14) -> 177000 | G14: =MAX(0,F14-Supuestos!$B$14) -> 176000 | H14: =MAX(0,G14-Supuestos!$B$14) -> 175000 | I14: =MAX(0,H14-Supuestos!$B$14) -> 174000 | J14: =MAX(0,I14-Supuestos!$B$14) -> 173000 | K14: =MAX(0,J14-Supuestos!$B$14) -> 172000 | ... O14: =MAX(0,N14-Supuestos!$B$14) -> 168000 | P14: =O14 -> 168000
A15: 2205_PROVEEDORES | B15: Proveedores | C15: =Supuestos!$B$24 -> 63000 | D15: =-PyG!D10*Supuestos!$B$10/30 -> 61206.347 | E15: =-PyG!E10*Supuestos!$B$10/30 -> 64258.64 | F15: =-PyG!F10*Supuestos!$B$10/30 -> 72397.447 | G15: =-PyG!G10*Supuestos!$B$10/30 -> 70876.967 | H15: =-PyG!H10*Supuestos!$B$10/30 -> 74607.333 | I15: =-PyG!I10*Supuestos!$B$10/30 -> 76817.22 | J15: =-PyG!J10*Supuestos!$B$10/30 -> 76011.216 | K15: =-PyG!K10*Supuestos!$B$10/30 -> 79173.851 | ... O15: =-PyG!O10*Supuestos!$B$10/30 -> 91529.723 | P15: =O15 -> 91529.723
A16: 2404_IMPUESTO_RENTA | B16: Impuesto de renta por pagar | C16: =Supuestos!$B$25 -> 0 | D16: =C16-PyG!D23 -> 774.5122 | E16: =D16-PyG!E23 -> 1790.7778 | F16: =E16-PyG!F23 -> 3551.464 | G16: =F16-PyG!G23 -> 5265.911 | H16: =G16-PyG!H23 -> 7289.121 | I16: =H16-PyG!I23 -> 9470.8348 | J16: =I16-PyG!J23 -> 11564.566 | K16: =J16-PyG!K23 -> 13910.956 | ... O16: =N16-PyG!O23 -> 24556.768 | P16: =O16 -> 24556.768
B17: Total pasivo | C17: =SUM(C14:C16) -> 243000 | D17: =SUM(D14:D16) -> 240980.86 | E17: =SUM(E14:E16) -> 244049.42 | F17: =SUM(F14:F16) -> 252948.91 | G17: =SUM(G14:G16) -> 252142.88 | H17: =SUM(H14:H16) -> 256896.45 | I17: =SUM(I14:I16) -> 260288.05 | J17: =SUM(J14:J16) -> 260575.78 | ... O17: =SUM(O14:O16) -> 284086.49 | P17: =O17 -> 284086.49
B19: Patrimonio
A20: 3105_CAPITAL | B20: Capital suscrito y pagado | C20: =Supuestos!$B$26 -> 200000 | D20: =C20 -> 200000 | E20: =D20 -> 200000 | F20: =E20 -> 200000 | G20: =F20 -> 200000 | H20: =G20 -> 200000 | I20: =H20 -> 200000 | J20: =I20 -> 200000 | K20: =J20 -> 200000 | ... P20: =O20 -> 200000
A21: 3705_UTILIDADES_ACUM | B21: Utilidades acumuladas | C21: =Supuestos!$B$27 -> 26000 | D21: =C21 -> 26000 | E21: =D21 -> 26000 | F21: =E21 -> 26000 | G21: =F21 -> 26000 | H21: =G21 -> 26000 | I21: =H21 -> 26000 | J21: =I21 -> 26000 | K21: =J21 -> 26000 | ... P21: =O21 -> 26000
A22: 3605_UTILIDAD_EJERCICIO | B22: Utilidad del ejercicio (acumulada en el año) | C22: 0 | D22: =SUM(PyG!$D$24:D$24) -> 1438.3798 | E22: =SUM(PyG!$D$24:E$24) -> 3325.7302 | F22: =SUM(PyG!$D$24:F$24) -> 6595.576 | G22: =SUM(PyG!$D$24:G$24) -> 9779.549 | H22: =SUM(PyG!$D$24:H$24) -> 13536.939 | I22: =SUM(PyG!$D$24:I$24) -> 17588.693 | J22: =SUM(PyG!$D$24:J$24) -> 21477.052 | K22: =SUM(PyG!$D$24:K$24) -> 25834.632 | ... O22: =SUM(PyG!$D$24:O$24) -> 45605.426 | P22: =O22 -> 45605.426
B23: Total patrimonio | C23: =SUM(C20:C22) -> 226000 | D23: =SUM(D20:D22) -> 227438.38 | E23: =SUM(E20:E22) -> 229325.73 | F23: =SUM(F20:F22) -> 232595.58 | G23: =SUM(G20:G22) -> 235779.55 | H23: =SUM(H20:H22) -> 239536.94 | I23: =SUM(I20:I22) -> 243588.69 | J23: =SUM(J20:J22) -> 247477.05 | ... O23: =SUM(O20:O22) -> 271605.43 | P23: =O23 -> 271605.43
B24: Total pasivo y patrimonio | C24: =C17+C23 -> 469000 | D24: =D17+D23 -> 468419.24 | E24: =E17+E23 -> 473375.15 | F24: =F17+F23 -> 485544.49 | G24: =G17+G23 -> 487922.43 | H24: =H17+H23 -> 496433.39 | I24: =I17+I23 -> 503876.75 | J24: =J17+J23 -> 508052.83 | ... O24: =O17+O23 -> 555691.92 | P24: =O24 -> 555691.92
B26: Control: activo − pasivo − patrimonio (debe ser 0) | C26: =ROUND(C11-C24,2) -> 0 | D26: =ROUND(D11-D24,2) -> 0 | E26: =ROUND(E11-E24,2) -> 0 | F26: =ROUND(F11-F24,2) -> 0 | G26: =ROUND(G11-G24,2) -> 0 | H26: =ROUND(H11-H24,2) -> 0 | I26: =ROUND(I11-I24,2) -> 0 | J26: =ROUND(J11-J24,2) -> 0 | ... O26: =ROUND(O11-O24,2) -> 0 | P26: =O26 -> 0

Sheet Flujo_Caja
A1: Flujo de caja 2026 (método indirecto) – FANALCA consolidado
A2: Millones de COP. Parte de la utilidad neta del P&L y de las variaciones del balance; la caja final alimenta el balance.
A4: Código | B4: Concepto | D4: Ene 2026 | E4: Feb 2026 | F4: Mar 2026 | G4: Abr 2026 | H4: May 2026 | I4: Jun 2026 | J4: Jul 2026 | K4: Ago 2026 | L4: Sep 2026 | M4: Oct 2026 | N4: Nov 2026 | O4: Dic 2026 | P4: Total 2026
B5: Actividades de operación
B6: Utilidad neta | D6: =PyG!D24 -> 1438.3798 | E6: =PyG!E24 -> 1887.3504 | F6: =PyG!F24 -> 3269.8458 | G6: =PyG!G24 -> 3183.973 | H6: =PyG!H24 -> 3757.39 | I6: =PyG!I24 -> 4051.7542 | J6: =PyG!J24 -> 3888.3588 | K6: =PyG!K24 -> 4357.5802 | ... O6: =PyG!O24 -> 4908.5312 | P6: =SUM(D6:O6) -> 45605.426
B7: (+) Depreciación | D7: =-PyG!D19 -> 3525 | E7: =-PyG!E19 -> 3550 | F7: =-PyG!F19 -> 3575 | G7: =-PyG!G19 -> 3600 | H7: =-PyG!H19 -> 3625 | I7: =-PyG!I19 -> 3650 | J7: =-PyG!J19 -> 3675 | K7: =-PyG!K19 -> 3700 | ... O7: =-PyG!O19 -> 3800 | P7: =SUM(D7:O7) -> 43950
B8: (−) Aumento de cuentas por cobrar | D8: =-(Balance!D7-Balance!C7) -> 16991.6 | E8: =-(Balance!E7-Balance!D7) -> -4039.8 | F8: =-(Balance!F7-Balance!E7) -> -10771.95 | G8: =-(Balance!G7-Balance!F7) -> 2012.4 | H8: =-(Balance!H7-Balance!G7) -> -4937.25 | I8: =-(Balance!I7-Balance!H7) -> -2924.85 | J8: =-(Balance!J7-Balance!I7) -> 1066.77 | K8: =-(Balance!K7-Balance!J7) -> -4185.84 | ... O8: =-(Balance!O7-Balance!N7) -> -12151.92 | P8: =SUM(D8:O8) -> -23142.28
B9: (−) Aumento de inventarios | D9: =-(Balance!D8-Balance!C8) -> 2552.384 | E9: =-(Balance!E8-Balance!D8) -> -3662.752 | F9: =-(Balance!F8-Balance!E8) -> -9766.568 | G9: =-(Balance!G8-Balance!F8) -> 1824.576 | H9: =-(Balance!H8-Balance!G8) -> -4476.44 | I9: =-(Balance!I8-Balance!H8) -> -2651.864 | J9: =-(Balance!J8-Balance!I8) -> 967.2048 | K9: =-(Balance!K8-Balance!J8) -> -3795.1616 | ... O9: =-(Balance!O8-Balance!N8) -> -11017.741 | P9: =SUM(D9:O9) -> -33835.667
B10: (+) Aumento de proveedores | D10: =(Balance!D15-Balance!C15) -> -1793.6533 | E10: =(Balance!E15-Balance!D15) -> 3052.2933 | F10: =(Balance!F15-Balance!E15) -> 8138.8067 | G10: =(Balance!G15-Balance!F15) -> -1520.48 | H10: =(Balance!H15-Balance!G15) -> 3730.3667 | I10: =(Balance!I15-Balance!H15) -> 2209.8867 | J10: =(Balance!J15-Balance!I15) -> -806.004 | K10: =(Balance!K15-Balance!J15) -> 3162.6347 | ... O10: =(Balance!O15-Balance!N15) -> 9181.4507 | P10: =SUM(D10:O10) -> 28529.723
B11: (+) Aumento de impuestos por pagar | D11: =(Balance!D16-Balance!C16) -> 774.5122 | E11: =(Balance!E16-Balance!D16) -> 1016.2656 | F11: =(Balance!F16-Balance!E16) -> 1760.6862 | G11: =(Balance!G16-Balance!F16) -> 1714.447 | H11: =(Balance!H16-Balance!G16) -> 2023.21 | I11: =(Balance!I16-Balance!H16) -> 2181.7138 | J11: =(Balance!J16-Balance!I16) -> 2093.7316 | K11: =(Balance!K16-Balance!J16) -> 2346.3894 | ... O11: =(Balance!O16-Balance!N16) -> 2643.0552 | P11: =SUM(D11:O11) -> 24556.768
B12: Flujo de caja de operación | D12: =SUM(D6:D11) -> 23488.223 | E12: =SUM(E6:E11) -> 1803.3573 | F12: =SUM(F6:F11) -> -3794.1793 | G12: =SUM(G6:G11) -> 10814.916 | H12: =SUM(H6:H11) -> 3722.2767 | I12: =SUM(I6:I11) -> 6516.6407 | J12: =SUM(J6:J11) -> 10885.061 | K12: =SUM(K6:K11) -> 5585.6027 | ... O12: =SUM(O6:O11) -> -2636.6237 | P12: =SUM(D12:O12) -> 85663.969
B14: Actividades de inversión
B15: (−) Compras de propiedad, planta y equipo | D15: =-(Balance!D9-Balance!C9) -> -3000 | E15: =-(Balance!E9-Balance!D9) -> -3000 | F15: =-(Balance!F9-Balance!E9) -> -3000 | G15: =-(Balance!G9-Balance!F9) -> -3000 | H15: =-(Balance!H9-Balance!G9) -> -3000 | I15: =-(Balance!I9-Balance!H9) -> -3000 | J15: =-(Balance!J9-Balance!I9) -> -3000 | K15: =-(Balance!K9-Balance!J9) -> -3000 | ... O15: =-(Balance!O9-Balance!N9) -> -3000 | P15: =SUM(D15:O15) -> -36000
B16: Flujo de caja de inversión | D16: =D15 -> -3000 | E16: =E15 -> -3000 | F16: =F15 -> -3000 | G16: =G15 -> -3000 | H16: =H15 -> -3000 | I16: =I15 -> -3000 | J16: =J15 -> -3000 | K16: =K15 -> -3000 | ... O16: =O15 -> -3000 | P16: =SUM(D16:O16) -> -36000
B18: Actividades de financiación
B19: (+/−) Variación de obligaciones financieras | D19: =(Balance!D14-Balance!C14) -> -1000 | E19: =(Balance!E14-Balance!D14) -> -1000 | F19: =(Balance!F14-Balance!E14) -> -1000 | G19: =(Balance!G14-Balance!F14) -> -1000 | H19: =(Balance!H14-Balance!G14) -> -1000 | I19: =(Balance!I14-Balance!H14) -> -1000 | J19: =(Balance!J14-Balance!I14) -> -1000 | K19: =(Balance!K14-Balance!J14) -> -1000 | ... O19: =(Balance!O14-Balance!N14) -> -1000 | P19: =SUM(D19:O19) -> -12000
B20: Flujo de caja de financiación | D20: =D19 -> -1000 | E20: =E19 -> -1000 | F20: =F19 -> -1000 | G20: =G19 -> -1000 | H20: =H19 -> -1000 | I20: =I19 -> -1000 | J20: =J19 -> -1000 | K20: =K19 -> -1000 | ... O20: =O19 -> -1000 | P20: =SUM(D20:O20) -> -12000
B22: Variación neta del efectivo | D22: =D12+D16+D20 -> 19488.223 | E22: =E12+E16+E20 -> -2196.6427 | F22: =F12+F16+F20 -> -7794.1793 | G22: =G12+G16+G20 -> 6814.916 | H22: =H12+H16+H20 -> -277.72333 | I22: =I12+I16+I20 -> 2516.6407 | J22: =J12+J16+J20 -> 6885.0612 | K22: =K12+K16+K20 -> 1585.6027 | ... O22: =O12+O16+O20 -> -6636.6237 | P22: =SUM(D22:O22) -> 37663.969
B23: Efectivo al inicio del mes | D23: =Supuestos!$B$18 -> 25000 | E23: =D24 -> 44488.223 | F23: =E24 -> 42291.58 | G23: =F24 -> 34497.401 | H23: =G24 -> 41312.317 | I23: =H24 -> 41034.593 | J23: =I24 -> 43551.234 | K23: =J24 -> 50436.295 | L23: =K24 -> 52021.898 | ... O23: =N24 -> 69300.593 | P23: =D23 -> 25000
B24: Efectivo al cierre del mes | D24: =D23+D22 -> 44488.223 | E24: =E23+E22 -> 42291.58 | F24: =F23+F22 -> 34497.401 | G24: =G23+G22 -> 41312.317 | H24: =H23+H22 -> 41034.593 | I24: =I23+I22 -> 43551.234 | J24: =J23+J22 -> 50436.295 | K24: =K23+K22 -> 52021.898 | ... O24: =O23+O22 -> 62663.969 | P24: =O24 -> 62663.969

Sheet Supuestos
A1: Supuestos de los reportes
A2: Celdas amarillas con texto azul: valores que usted puede cambiar. Todo lo demás se calcula.
A4: Supuesto | B4: Valor | C4: Nota
A5: Escala de los reportes (COP por unidad) | B5: 1000000 | C5: Los reportes se muestran en millones de COP; las plantillas de carga van en COP.
A6: Costo de ventas (% de los ingresos) | B6: 0.68 | C6: Supuesto de ejemplo. En SAC suele venir del modelo de costos o de un data action.
A7: Tasa de impuesto de renta | B7: 0.35 | C7: Tarifa general de renta en Colombia (35 %). Ajuste según su caso.
A8: Días de cartera (sobre ingresos) | B8: 45
A9: Días de inventario (sobre costo de ventas) | B9: 60
A10: Días de proveedores (sobre costo de ventas) | B10: 50
A11: Inversión en PP&E mensual (millones COP) | B11: 3000
A12: Vida útil de la PP&E (años) | B12: 10 | C12: Depreciación en línea recta sobre el saldo bruto.
A13: Tasa de interés anual de la deuda | B13: 0.12
A14: Amortización mensual de deuda (millones COP) | B14: 1000
A16: Balance de apertura al 31 dic 2025 (millones COP)
A17: Cuenta | B17: Saldo | C17: Nota
A18: Efectivo y equivalentes | B18: 25000
A19: Cuentas por cobrar clientes | B19: 98000
A20: Inventarios | B20: 76000
A21: Propiedad, planta y equipo (bruto) | B21: 420000
A22: Depreciación acumulada (negativo) | B22: -150000
A23: Obligaciones financieras | B23: 180000
A24: Proveedores | B24: 63000
A25: Impuesto de renta por pagar | B25: 0
A26: Capital suscrito y pagado | B26: 200000
A27: Utilidades acumuladas (cuadra la apertura) | B27: =Supuestos!$B$18+Supuestos!$B$19+Supuestos!$B$20+Supuestos!$B$21+Supuestos!$B$22-Supuestos!$B$23-Supuestos!$B$24-Supuestos!$B$25-Supuestos!$B$26 -> 26000 | C27: Fórmula: activos − pasivos − capital.

Sheet Listas
A1: Listas de miembros (ejemplo)
A2: Reemplace por los IDs reales de las dimensiones de sus modelos en SAC. Alimentan las listas desplegables de las plantillas.
A4: Sociedades | B4: Cebes | C4: Cecos | D4: Ratio | E4: Auditoria | F4: Versión | H4: Cuentas_Egresos | I4: Descripción | J4: Grupo P&L (propiedad) | L4: Cuentas_EF | M4: Descripción | N4: Tipo
A5: FN_MOTOS | B5: CB_MOTOS | C5: CC_PLANTA | D5: UNIDADES | E5: PRESUPUESTO_EXCEL | F5: public.Presupuesto_2026 | H5: 5105_SALARIOS | I5: Salarios y prestaciones | J5: Gastos de administración | L5: 1105_CAJA | M5: Efectivo y equivalentes | N5: Activo
A6: FN_AUTOS | B6: CB_AUTOS | C6: CC_ADMIN | D6: PRECIO | E6: MANUAL | F6: public.Forecast_2026 | H6: 5110_HONORARIOS | I6: Honorarios | J6: Gastos de administración | L6: 1305_CLIENTES | M6: Cuentas por cobrar clientes | N6: Activo
A7: FN_TUBOS | B7: CB_TUBERIA | C7: CC_VENTAS | D7: ING_VENTAS_NAL | E7: CALCULADO_DA | F7: public.PRUEBAS | H7: 5135_SERVICIOS | I7: Servicios públicos | J7: Gastos de administración | L7: 1435_INVENTARIOS | M7: Inventarios | N7: Activo
B8: CB_CORPORATIVO | C8: CC_LOGISTICA | H8: 5145_MANTENIMIENTO | I8: Mantenimiento y reparaciones | J8: Gastos de administración | L8: 1520_PPE | M8: Propiedad, planta y equipo (bruto) | N8: Activo
H9: 5205_SALARIOS_VENTAS | I9: Salarios fuerza de ventas | J9: Gastos de ventas | L9: 1592_DEP_ACUMULADA | M9: Depreciación acumulada | N9: Activo
H10: 5235_PUBLICIDAD | I10: Publicidad y mercadeo | J10: Gastos de ventas | L10: 2105_OBLIGACIONES_FIN | M10: Obligaciones financieras | N10: Pasivo
H11: 5250_FLETES | I11: Fletes y transporte | J11: Gastos de ventas | L11: 2205_PROVEEDORES | M11: Proveedores | N11: Pasivo
L12: 2404_IMPUESTO_RENTA | M12: Impuesto de renta por pagar | N12: Pasivo
L13: 3105_CAPITAL | M13: Capital suscrito y pagado | N13: Patrimonio
L14: 3705_UTILIDADES_ACUM | M14: Utilidades acumuladas | N14: Patrimonio
L15: 3605_UTILIDAD_EJERCICIO | M15: Utilidad del ejercicio | N15: Patrimonio
